powerfulseal/__init__.py
powerfulseal/version.py
powerfulseal/cli/__init__.py
powerfulseal/cli/__main__.py
powerfulseal/cli/pscmd.py
powerfulseal/clouddrivers/__init__.py
powerfulseal/clouddrivers/aws_driver.py
powerfulseal/clouddrivers/azure_driver.py
powerfulseal/clouddrivers/driver.py
powerfulseal/clouddrivers/gcp_driver.py
powerfulseal/clouddrivers/no_cloud_driver.py
powerfulseal/clouddrivers/open_stack_driver.py
powerfulseal/execute/__init__.py
powerfulseal/execute/abstract_executor.py
powerfulseal/execute/kubernetes_executor.py
powerfulseal/execute/ssh_executor.py
powerfulseal/k8s/__init__.py
powerfulseal/k8s/k8s_client.py
powerfulseal/k8s/k8s_inventory.py
powerfulseal/k8s/metrics_server_client.py
powerfulseal/k8s/pod.py
powerfulseal/metriccollectors/__init__.py
powerfulseal/metriccollectors/collector.py
powerfulseal/metriccollectors/datadog_collector.py
powerfulseal/metriccollectors/prometheus_collector.py
powerfulseal/metriccollectors/stdout_collector.py
powerfulseal/node/__init__.py
powerfulseal/node/inventory.py
powerfulseal/node/node.py
powerfulseal/node/node_inventory.py
powerfulseal/policy/__init__.py
powerfulseal/policy/action_abstract.py
powerfulseal/policy/action_kubectl.py
powerfulseal/policy/action_nodes.py
powerfulseal/policy/action_nodes_pods.py
powerfulseal/policy/action_pods.py
powerfulseal/policy/action_probe_http.py
powerfulseal/policy/label_runner.py
powerfulseal/policy/policy_runner.py
powerfulseal/policy/ps-schema.yaml
powerfulseal/policy/scenario.py
powerfulseal/web/__init__.py
powerfulseal/web/server.py
powerfulseal/web/dist/base.html.j2
powerfulseal/web/dist/index.html.j2
powerfulseal/web/dist/logs.html.j2
powerfulseal/web/dist/static/bootstrap/4.4.1/css/bootstrap.min.css
powerfulseal/web/dist/static/schema/index.html
powerfulseal/web/dist/static/schema/schema_doc.css
powerfulseal/web/dist/static/schema/schema_doc.min.js
tests/__init__.py
tests/fixtures.py
tests/cli/__init__.py
tests/cli/test_args.py
tests/cli/test_kubeconfig.py
powerfulseal-3.1.0.dist-info/LICENSE
powerfulseal-3.1.0.dist-info/METADATA
powerfulseal-3.1.0.dist-info/WHEEL
powerfulseal-3.1.0.dist-info/entry_points.txt
powerfulseal-3.1.0.dist-info/top_level.txt
powerfulseal-3.1.0.dist-info/RECORD
