Metadata-Version: 2.1
Name: powerfulseal
Version: 3.1.0
Summary: PowerfulSeal - a powerful testing tool for Kubernetes clusters
Home-page: https://github.com/bloomberg/powerfulseal
Author: Mikolaj Pawlikowski
Author-email: mikolaj@pawlikowski.pl
License: Apache 2.0
Project-URL: Source, https://github.com/bloomberg/powerfulseal
Project-URL: Tracker, https://github.com/bloomberg/powerfulseal/issues
Platform: UNKNOWN
Classifier: Development Status :: 4 - Beta
Classifier: Intended Audience :: Developers
Classifier: Topic :: Software Development :: Quality Assurance
Classifier: Programming Language :: Python :: 3
Requires-Python: >=3
Requires-Dist: ConfigArgParse (<1,>=0.11.0)
Requires-Dist: Flask (<2,>=1.0.0)
Requires-Dist: termcolor (<2,>=1.1.0)
Requires-Dist: openstacksdk (<1,>=0.10.0)
Requires-Dist: spur (<1,>=0.3.20)
Requires-Dist: kubernetes (<12.0.0,>=11.0.0)
Requires-Dist: PyYAML (<6,>=5.1.2)
Requires-Dist: jsonschema (<4,>=3.0.2)
Requires-Dist: boto3 (<2.0.0,>=1.5.15)
Requires-Dist: azure-common (<2.0.0,>=1.1.23)
Requires-Dist: azure-mgmt-resource (<3.0.0,>=2.2.0)
Requires-Dist: azure-mgmt-network (<3.0.0,>=2.7.0)
Requires-Dist: azure-mgmt-compute (<5.0.0,>=4.6.2)
Requires-Dist: future (<1,>=0.16.0)
Requires-Dist: requests (<3,>=2.21.0)
Requires-Dist: prometheus-client (<0.4.0,>=0.3.0)
Requires-Dist: flask-cors (<4,>=3.0.6)
Requires-Dist: coloredlogs (<11.0.0,>=10.0.0)
Requires-Dist: paramiko (<3,>=2.5.0)
Requires-Dist: google-api-python-client (>=1.7.8)
Requires-Dist: google-auth (>=1.6.2)
Requires-Dist: google-auth-httplib2 (>=0.0.3)
Requires-Dist: oauth2client (>=4.1.3)
Requires-Dist: datadog (<1.0.0,>=0.29.0)
Requires-Dist: python-dateutil (<2.7.0,>=2.5.3)
Provides-Extra: testing
Requires-Dist: pytest (<4,>=3.0) ; extra == 'testing'
Requires-Dist: pytest-cov (<3,>=2.5) ; extra == 'testing'
Requires-Dist: mock (<5,>=4) ; extra == 'testing'
